uniface/__init__.py
uniface/analyzer.py
uniface/common.py
uniface/constants.py
uniface/face_utils.py
uniface/log.py
uniface/model_store.py
uniface/onnx_utils.py
uniface/py.typed
uniface/types.py
uniface/visualization.py
uniface/attribute/__init__.py
uniface/attribute/age_gender.py
uniface/attribute/base.py
uniface/attribute/emotion.py
uniface/attribute/fairface.py
uniface/detection/__init__.py
uniface/detection/base.py
uniface/detection/retinaface.py
uniface/detection/scrfd.py
uniface/detection/yolov5.py
uniface/detection/yolov8.py
uniface/gaze/__init__.py
uniface/gaze/base.py
uniface/gaze/models.py
uniface/landmark/__init__.py
uniface/landmark/base.py
uniface/landmark/models.py
uniface/parsing/__init__.py
uniface/parsing/base.py
uniface/parsing/bisenet.py
uniface/privacy/__init__.py
uniface/privacy/blur.py
uniface/recognition/__init__.py
uniface/recognition/adaface.py
uniface/recognition/base.py
uniface/recognition/models.py
uniface/spoofing/__init__.py
uniface/spoofing/base.py
uniface/spoofing/minifasnet.py
uniface-2.2.1.dist-info/licenses/LICENSE
uniface-2.2.1.dist-info/METADATA
uniface-2.2.1.dist-info/WHEEL
uniface-2.2.1.dist-info/top_level.txt
uniface-2.2.1.dist-info/RECORD
