Metadata-Version: 2.4
Name: uniface
Version: 2.2.1
Summary: UniFace: A Comprehensive Library for Face Detection, Recognition, Landmark Analysis, Face Parsing, Gaze Estimation, Age, and Gender Detection
Author-email: Yakhyokhuja Valikhujaev <yakhyo9696@gmail.com>
Maintainer-email: Yakhyokhuja Valikhujaev <yakhyo9696@gmail.com>
License-Expression: MIT
Project-URL: Homepage, https://github.com/yakhyo/uniface
Project-URL: Repository, https://github.com/yakhyo/uniface
Project-URL: Documentation, https://github.com/yakhyo/uniface/blob/main/README.md
Project-URL: Quick Start, https://github.com/yakhyo/uniface/blob/main/QUICKSTART.md
Project-URL: Model Zoo, https://github.com/yakhyo/uniface/blob/main/MODELS.md
Keywords: face-detection,face-recognition,facial-landmarks,face-parsing,face-segmentation,gaze-estimation,age-detection,gender-detection,computer-vision,deep-learning,onnx,onnxruntime,face-analysis,bisenet
Classifier: Development Status :: 4 - Beta
Classifier: Intended Audience :: Developers
Classifier: Intended Audience :: Science/Research
Classifier: Operating System :: OS Independent
Classifier: Programming Language :: Python :: 3
Classifier: Programming Language :: Python :: 3.10
Classifier: Programming Language :: Python :: 3.11
Classifier: Programming Language :: Python :: 3.12
Classifier: Programming Language :: Python :: 3.13
Requires-Python: <3.14,>=3.10
License-File: LICENSE
Requires-Dist: numpy>=1.21.0
Requires-Dist: opencv-python>=4.5.0
Requires-Dist: onnx>=1.12.0
Requires-Dist: onnxruntime>=1.16.0
Requires-Dist: scikit-image>=0.19.0
Requires-Dist: requests>=2.28.0
Requires-Dist: tqdm>=4.64.0
Provides-Extra: dev
Requires-Dist: pytest>=7.0.0; extra == "dev"
Requires-Dist: ruff>=0.4.0; extra == "dev"
Provides-Extra: gpu
Requires-Dist: onnxruntime-gpu>=1.16.0; extra == "gpu"
Dynamic: license-file
